{"v":"4.8.0","meta":{"g":"LottieFiles AE ","a":"","k":"","d":"","tc":""},"fr":60,"ip":0,"op":600,"w":600,"h":600,"nm":"Comp 1","ddd":0,"assets":[],"layers":[{"ddd":0,"ind":1,"ty":4,"nm":"right Outlines","sr":1,"ks":{"o":{"a":0,"k":100,"ix":11},"r":{"a":0,"k":0,"ix":10},"p":{"a":1,"k":[{"i":{"x":0,"y":1},"o":{"x":0.333,"y":0},"t":194,"s":[309.225,242.7,0],"to":[-2.167,0,0],"ti":[2.167,0,0]},{"i":{"x":0,"y":0},"o":{"x":0.333,"y":0.333},"t":212,"s":[296.225,242.7,0],"to":[0,0,0],"ti":[0,0,0]},{"i":{"x":0,"y":1},"o":{"x":0.333,"y":0},"t":295,"s":[296.225,242.7,0],"to":[-30.167,0,0],"ti":[30.167,0,0]},{"t":313,"s":[115.225,242.7,0]}],"ix":2},"a":{"a":0,"k":[128.733,110,0],"ix":1},"s":{"a":1,"k":[{"i":{"x":[0,0.667,0.667],"y":[1,1,1]},"o":{"x":[0.333,0.333,0.333],"y":[0,0,0]},"t":102,"s":[0,227,100]},{"i":{"x":[0.833,0.833,0.833],"y":[1,1,1]},"o":{"x":[0.333,0.333,0.333],"y":[0,0,0]},"t":114,"s":[227,227,100]},{"i":{"x":[0.833,0.833,0.833],"y":[1,1,1]},"o":{"x":[0.167,0.167,0.167],"y":[0,0,0]},"t":194,"s":[227,227,100]},{"t":212,"s":[204,227,100]}],"ix":6}},"ao":0,"shapes":[{"ty":"gr","it":[{"ind":0,"ty":"sh","ix":1,"ks":{"a":0,"k":{"i":[[0.727,0],[0,0],[0,0.726],[0,0],[-0.727,0],[0,0],[0,-0.726],[0,0]],"o":[[0,0],[-0.727,0],[0,0],[0,-0.726],[0,0],[0.727,0],[0,0],[0,0.726]],"v":[[25.686,2],[-25.685,2],[-27,0.686],[-27,-0.686],[-25.685,-2],[25.686,-2],[27,-0.686],[27,0.686]],"c":true},"ix":2},"nm":"Path 1","mn":"ADBE Vector Shape - Group","hd":false},{"ty":"fl","c":{"a":0,"k":[0.620000023935,0.552999997606,1,1],"ix":4},"o":{"a":0,"k":100,"ix":5},"r":1,"bm":0,"nm":"Fill 1","mn":"ADBE Vector Graphic - Fill","hd":false},{"ty":"tr","p":{"a":0,"k":[154.999,133],"ix":2},"a":{"a":0,"k":[0,0],"ix":1},"s":{"a":0,"k":[100,100],"ix":3},"r":{"a":0,"k":0,"ix":6},"o":{"a":0,"k":100,"ix":7},"sk":{"a":0,"k":0,"ix":4},"sa":{"a":0,"k":0,"ix":5},"nm":"Transform"}],"nm":"Group 1","np":2,"cix":2,"bm":0,"ix":1,"mn":"ADBE Vector Group","hd":false},{"ty":"gr","it":[{"ind":0,"ty":"sh","ix":1,"ks":{"a":0,"k":{"i":[[0.369,0],[0,0],[0,0.369],[0,0],[-0.369,0],[0,0],[0,-0.369],[0,0]],"o":[[0,0],[-0.369,0],[0,0],[0,-0.369],[0,0],[0.369,0],[0,0],[0,0.369]],"v":[[6.331,2],[-6.331,2],[-7,1.331],[-7,-1.331],[-6.331,-2],[6.331,-2],[7,-1.331],[7,1.331]],"c":true},"ix":2},"nm":"Path 1","mn":"ADBE Vector Shape - Group","hd":false},{"ty":"fl","c":{"a":0,"k":[0.620000023935,0.552999997606,1,1],"ix":4},"o":{"a":0,"k":100,"ix":5},"r":1,"bm":0,"nm":"Fill 1","mn":"ADBE Vector Graphic - Fill","hd":false},{"ty":"tr","p":{"a":0,"k":[200,133],"ix":2},"a":{"a":0,"k":[0,0],"ix":1},"s":{"a":0,"k":[100,100],"ix":3},"r":{"a":0,"k":0,"ix":6},"o":{"a":0,"k":100,"ix":7},"sk":{"a":0,"k":0,"ix":4},"sa":{"a":0,"k":0,"ix":5},"nm":"Transform"}],"nm":"Group 2","np":2,"cix":2,"bm":0,"ix":2,"mn":"ADBE Vector Group","hd":false},{"ty":"gr","it":[{"ind":0,"ty":"sh","ix":1,"ks":{"a":0,"k":{"i":[[2.845,0],[0,0],[0,2.844],[0,0],[-2.845,0],[0,0],[0,-2.844],[0,0]],"o":[[0,0],[-2.845,0],[0,0],[0,-2.844],[0,0],[2.845,0],[0,0],[0,2.844]],"v":[[34.35,21],[-34.349,21],[-39.5,15.85],[-39.5,-15.85],[-34.349,-21],[34.35,-21],[39.5,-15.85],[39.5,15.85]],"c":true},"ix":2},"nm":"Path 1","mn":"ADBE Vector Shape - Group","hd":false},{"ty":"fl","c":{"a":0,"k":[0.870999983245,0.862999949736,1,1],"ix":4},"o":{"a":0,"k":100,"ix":5},"r":1,"bm":0,"nm":"Fill 1","mn":"ADBE Vector Graphic - Fill","hd":false},{"ty":"tr","p":{"a":0,"k":[167.5,106],"ix":2},"a":{"a":0,"k":[0,0],"ix":1},"s":{"a":0,"k":[100,100],"ix":3},"r":{"a":0,"k":0,"ix":6},"o":{"a":0,"k":100,"ix":7},"sk":{"a":0,"k":0,"ix":4},"sa":{"a":0,"k":0,"ix":5},"nm":"Transform"}],"nm":"Group 3","np":2,"cix":2,"bm":0,"ix":3,"mn":"ADBE Vector Group","hd":false}],"ip":6,"op":308,"st":6,"bm":0},{"ddd":0,"ind":2,"ty":4,"nm":"left Outlines","sr":1,"ks":{"o":{"a":1,"k":[{"i":{"x":[0.833],"y":[0.833]},"o":{"x":[0.167],"y":[0.167]},"t":558,"s":[100]},{"t":593,"s":[0]}],"ix":11},"r":{"a":0,"k":0,"ix":10},"p":{"a":1,"k":[{"i":{"x":0.833,"y":0.833},"o":{"x":0.167,"y":0.167},"t":295,"s":[111.005,242.7,0],"to":[19,0,0],"ti":[-19,0,0]},{"i":{"x":0.833,"y":0.833},"o":{"x":0.167,"y":0.167},"t":330,"s":[225.005,242.7,0],"to":[0,0,0],"ti":[0,0,0]},{"i":{"x":0.833,"y":0.833},"o":{"x":0.167,"y":0.167},"t":558,"s":[225.005,242.7,0],"to":[75.5,0,0],"ti":[-75.5,0,0]},{"t":593,"s":[678.005,242.7,0]}],"ix":2},"a":{"a":0,"k":[41.412,110,0],"ix":1},"s":{"a":1,"k":[{"i":{"x":[0,0.667,0.667],"y":[1,1,1]},"o":{"x":[0.333,0.333,0.333],"y":[0,0,0]},"t":96,"s":[0,227,100]},{"i":{"x":[0.833,0.833,0.833],"y":[1,1,1]},"o":{"x":[0.333,0.333,0.333],"y":[0,0,0]},"t":108,"s":[227,227,100]},{"i":{"x":[0.833,0.833,0.833],"y":[1,1,1]},"o":{"x":[0.167,0.167,0.167],"y":[0,0,0]},"t":188,"s":[227,227,100]},{"i":{"x":[0.636,0.636,0.636],"y":[1,1,1]},"o":{"x":[0.158,0.158,0.158],"y":[0,0,0]},"t":206,"s":[204,227,100]},{"i":{"x":[0.81,0.81,0.81],"y":[1,1,1]},"o":{"x":[0.438,0.438,0.438],"y":[0,0,0]},"t":295,"s":[204,227,100]},{"t":330,"s":[178,227,100]}],"ix":6}},"ao":0,"shapes":[{"ty":"gr","it":[{"ind":0,"ty":"sh","ix":1,"ks":{"a":0,"k":{"i":[[0.37,0],[0,0],[0,0.369],[0,0],[-0.37,0],[0,0],[0,-0.369],[0,0]],"o":[[0,0],[-0.37,0],[0,0],[0,-0.369],[0,0],[0.37,0],[0,0],[0,0.369]],"v":[[6.331,2],[-6.331,2],[-7,1.331],[-7,-1.331],[-6.331,-2],[6.331,-2],[7,-1.331],[7,1.331]],"c":true},"ix":2},"nm":"Path 1","mn":"ADBE Vector Shape - Group","hd":false},{"ty":"fl","c":{"a":0,"k":[0.620000023935,0.552999997606,1,1],"ix":4},"o":{"a":0,"k":100,"ix":5},"r":1,"bm":0,"nm":"Fill 1","mn":"ADBE Vector Graphic - Fill","hd":false},{"ty":"tr","p":{"a":0,"k":[114,133],"ix":2},"a":{"a":0,"k":[0,0],"ix":1},"s":{"a":0,"k":[100,100],"ix":3},"r":{"a":0,"k":0,"ix":6},"o":{"a":0,"k":100,"ix":7},"sk":{"a":0,"k":0,"ix":4},"sa":{"a":0,"k":0,"ix":5},"nm":"Transform"}],"nm":"Group 1","np":2,"cix":2,"bm":0,"ix":1,"mn":"ADBE Vector Group","hd":false},{"ty":"gr","it":[{"ind":0,"ty":"sh","ix":1,"ks":{"a":0,"k":{"i":[[0.726,0],[0,0],[0,0.726],[0,0],[-0.726,0],[0,0],[0,-0.726],[0,0]],"o":[[0,0],[-0.726,0],[0,0],[0,-0.726],[0,0],[0.726,0],[0,0],[0,0.726]],"v":[[25.686,2],[-25.686,2],[-27,0.686],[-27,-0.686],[-25.686,-2],[25.686,-2],[27,-0.686],[27,0.686]],"c":true},"ix":2},"nm":"Path 1","mn":"ADBE Vector Shape - Group","hd":false},{"ty":"fl","c":{"a":0,"k":[0.620000023935,0.552999997606,1,1],"ix":4},"o":{"a":0,"k":100,"ix":5},"r":1,"bm":0,"nm":"Fill 1","mn":"ADBE Vector Graphic - Fill","hd":false},{"ty":"tr","p":{"a":0,"k":[69,133],"ix":2},"a":{"a":0,"k":[0,0],"ix":1},"s":{"a":0,"k":[100,100],"ix":3},"r":{"a":0,"k":0,"ix":6},"o":{"a":0,"k":100,"ix":7},"sk":{"a":0,"k":0,"ix":4},"sa":{"a":0,"k":0,"ix":5},"nm":"Transform"}],"nm":"Group 2","np":2,"cix":2,"bm":0,"ix":2,"mn":"ADBE Vector Group","hd":false},{"ty":"gr","it":[{"ind":0,"ty":"sh","ix":1,"ks":{"a":0,"k":{"i":[[2.844,0],[0,0],[0,2.844],[0,0],[-2.844,0],[0,0],[0,-2.844],[0,0]],"o":[[0,0],[-2.844,0],[0,0],[0,-2.844],[0,0],[2.844,0],[0,0],[0,2.844]],"v":[[34.35,21],[-34.35,21],[-39.5,15.85],[-39.5,-15.85],[-34.35,-21],[34.35,-21],[39.5,-15.85],[39.5,15.85]],"c":true},"ix":2},"nm":"Path 1","mn":"ADBE Vector Shape - Group","hd":false},{"ty":"fl","c":{"a":0,"k":[0.870999983245,0.862999949736,1,1],"ix":4},"o":{"a":0,"k":100,"ix":5},"r":1,"bm":0,"nm":"Fill 1","mn":"ADBE Vector Graphic - Fill","hd":false},{"ty":"tr","p":{"a":0,"k":[81.5,106],"ix":2},"a":{"a":0,"k":[0,0],"ix":1},"s":{"a":0,"k":[100,100],"ix":3},"r":{"a":0,"k":0,"ix":6},"o":{"a":0,"k":100,"ix":7},"sk":{"a":0,"k":0,"ix":4},"sa":{"a":0,"k":0,"ix":5},"nm":"Transform"}],"nm":"Group 3","np":2,"cix":2,"bm":0,"ix":3,"mn":"ADBE Vector Group","hd":false}],"ip":0,"op":600,"st":0,"bm":0},{"ddd":0,"ind":3,"ty":4,"nm":"bottom Outlines","sr":1,"ks":{"o":{"a":1,"k":[{"i":{"x":[0.833],"y":[0.833]},"o":{"x":[0.167],"y":[0.167]},"t":558,"s":[100]},{"t":593,"s":[0]}],"ix":11},"r":{"a":0,"k":0,"ix":10},"p":{"a":1,"k":[{"i":{"x":0.667,"y":1},"o":{"x":0.333,"y":0},"t":194,"s":[300.616,309.31,0],"to":[-2.167,0,0],"ti":[2.167,0,0]},{"i":{"x":0.667,"y":0.667},"o":{"x":0.333,"y":0.333},"t":212,"s":[287.616,309.31,0],"to":[0,0,0],"ti":[0,0,0]},{"i":{"x":0.667,"y":1},"o":{"x":0.333,"y":0},"t":295,"s":[287.616,309.31,0],"to":[0,0,0],"ti":[0,0,0]},{"i":{"x":0.667,"y":0.667},"o":{"x":0.333,"y":0.333},"t":330,"s":[296.616,309.31,0],"to":[0,0,0],"ti":[0,0,0]},{"i":{"x":0.667,"y":1},"o":{"x":0.333,"y":0},"t":558,"s":[296.616,309.31,0],"to":[0,0,0],"ti":[0,0,0]},{"t":593,"s":[749.616,309.31,0]}],"ix":2},"a":{"a":0,"k":[124.941,139.344,0],"ix":1},"s":{"a":1,"k":[{"i":{"x":[0,0,0.667],"y":[1,1,1]},"o":{"x":[0.333,0.333,0.333],"y":[0,0,0]},"t":108,"s":[227,0,100]},{"i":{"x":[0.833,0.833,0.833],"y":[1,1,1]},"o":{"x":[0.333,0.333,0.333],"y":[0,0,0]},"t":120,"s":[227,227,100]},{"i":{"x":[0.833,0.833,0.833],"y":[1,1,1]},"o":{"x":[0.167,0.167,0.167],"y":[0,0,0]},"t":194,"s":[227,227,100]},{"i":{"x":[0.631,0.631,0.631],"y":[1,1,1]},"o":{"x":[0.158,0.158,0.158],"y":[0,0,0]},"t":212,"s":[208,227,100]},{"i":{"x":[0.813,0.813,0.813],"y":[1,1,1]},"o":{"x":[0.437,0.437,0.437],"y":[0,0,0]},"t":295,"s":[208,227,100]},{"t":330,"s":[82,227,100]}],"ix":6}},"ao":0,"shapes":[{"ty":"gr","it":[{"ind":0,"ty":"sh","ix":1,"ks":{"a":0,"k":{"i":[[1.94,0],[0,0],[0,1.941],[0,0],[-1.94,0],[0,0],[0,-1.941],[0,0]],"o":[[0,0],[-1.94,0],[0,0],[0,-1.941],[0,0],[1.94,0],[0,0],[0,1.941]],"v":[[78.987,14],[-78.988,14],[-82.5,10.487],[-82.5,-10.487],[-78.988,-14],[78.987,-14],[82.5,-10.487],[82.5,10.487]],"c":true},"ix":2},"nm":"Path 1","mn":"ADBE Vector Shape - Group","hd":false},{"ty":"fl","c":{"a":0,"k":[0.870999983245,0.862999949736,1,1],"ix":4},"o":{"a":0,"k":100,"ix":5},"r":1,"bm":0,"nm":"Fill 1","mn":"ADBE Vector Graphic - Fill","hd":false},{"ty":"tr","p":{"a":0,"k":[124.5,153],"ix":2},"a":{"a":0,"k":[0,0],"ix":1},"s":{"a":0,"k":[100,100],"ix":3},"r":{"a":0,"k":0,"ix":6},"o":{"a":0,"k":100,"ix":7},"sk":{"a":0,"k":0,"ix":4},"sa":{"a":0,"k":0,"ix":5},"nm":"Transform"}],"nm":"Group 1","np":2,"cix":2,"bm":0,"ix":1,"mn":"ADBE Vector Group","hd":false}],"ip":0,"op":600,"st":0,"bm":0},{"ddd":0,"ind":4,"ty":4,"nm":"logo Outlines","sr":1,"ks":{"o":{"a":1,"k":[{"i":{"x":[0.833],"y":[0.833]},"o":{"x":[0.167],"y":[0.167]},"t":558,"s":[100]},{"t":593,"s":[0]}],"ix":11},"r":{"a":0,"k":0,"ix":10},"p":{"a":1,"k":[{"i":{"x":0.833,"y":0.833},"o":{"x":0.167,"y":0.167},"t":295,"s":[112.196,165.52,0],"to":[19.5,0,0],"ti":[-19.5,0,0]},{"i":{"x":0.833,"y":0.833},"o":{"x":0.167,"y":0.167},"t":330,"s":[229.196,165.52,0],"to":[0,0,0],"ti":[0,0,0]},{"i":{"x":0.833,"y":0.833},"o":{"x":0.167,"y":0.167},"t":558,"s":[229.196,165.52,0],"to":[75.5,0,0],"ti":[-75.5,0,0]},{"t":593,"s":[682.196,165.52,0]}],"ix":2},"a":{"a":0,"k":[41.936,76,0],"ix":1},"s":{"a":1,"k":[{"i":{"x":[0,0.667,0.667],"y":[1,1,1]},"o":{"x":[0.333,0.333,0.333],"y":[0,0,0]},"t":90,"s":[0,227,100]},{"i":{"x":[0.73,0.73,0.73],"y":[1,1,1]},"o":{"x":[0.306,0.306,0.306],"y":[0,0,0]},"t":102,"s":[227,227,100]},{"i":{"x":[0.764,0.764,0.764],"y":[1,1,1]},"o":{"x":[0.418,0.418,0.418],"y":[0,0,0]},"t":194,"s":[227,227,100]},{"i":{"x":[0.631,0.631,0.631],"y":[1,1,1]},"o":{"x":[0.158,0.158,0.158],"y":[0,0,0]},"t":212,"s":[168,227,100]},{"i":{"x":[0.813,0.813,0.813],"y":[1,1,1]},"o":{"x":[0.437,0.437,0.437],"y":[0,0,0]},"t":295,"s":[168,227,100]},{"t":330,"s":[105,227,100]}],"ix":6}},"ao":0,"shapes":[{"ty":"gr","it":[{"ind":0,"ty":"sh","ix":1,"ks":{"a":0,"k":{"i":[[0.697,0],[0,0],[0,0.698],[0,0],[-0.697,0],[0,0],[0,-0.698],[0,0]],"o":[[0,0],[-0.697,0],[0,0],[0,-0.698],[0,0],[0.697,0],[0,0],[0,0.698]],"v":[[35.237,4],[-35.238,4],[-36.5,2.737],[-36.5,-2.737],[-35.238,-4],[35.237,-4],[36.5,-2.737],[36.5,2.737]],"c":true},"ix":2},"nm":"Path 1","mn":"ADBE Vector Shape - Group","hd":false},{"ty":"fl","c":{"a":0,"k":[0.620000023935,0.552999997606,1,1],"ix":4},"o":{"a":0,"k":100,"ix":5},"r":1,"bm":0,"nm":"Fill 1","mn":"ADBE Vector Graphic - Fill","hd":false},{"ty":"tr","p":{"a":0,"k":[78.5,76],"ix":2},"a":{"a":0,"k":[0,0],"ix":1},"s":{"a":0,"k":[100,100],"ix":3},"r":{"a":0,"k":0,"ix":6},"o":{"a":0,"k":100,"ix":7},"sk":{"a":0,"k":0,"ix":4},"sa":{"a":0,"k":0,"ix":5},"nm":"Transform"}],"nm":"Group 1","np":2,"cix":2,"bm":0,"ix":1,"mn":"ADBE Vector Group","hd":false}],"ip":0,"op":600,"st":0,"bm":0},{"ddd":0,"ind":5,"ty":4,"nm":"keyboard Outlines","sr":1,"ks":{"o":{"a":0,"k":100,"ix":11},"r":{"a":0,"k":0,"ix":10},"p":{"a":1,"k":[{"i":{"x":0.263,"y":1},"o":{"x":0.333,"y":0},"t":0,"s":[913.75,276.75,0],"to":[-108.167,0,0],"ti":[98.5,0,0]},{"i":{"x":0.985,"y":1},"o":{"x":0.333,"y":0},"t":18,"s":[264.75,276.75,0],"to":[-98.5,0,0],"ti":[-6,0,0]},{"i":{"x":1,"y":1},"o":{"x":0.333,"y":0},"t":26,"s":[322.75,276.75,0],"to":[6,0,0],"ti":[3.667,0,0]},{"i":{"x":0.852,"y":0.852},"o":{"x":0.167,"y":0.167},"t":33,"s":[300.75,276.75,0],"to":[0,0,0],"ti":[0,0,0]},{"i":{"x":0,"y":1},"o":{"x":0.167,"y":0},"t":120,"s":[300.75,276.75,0],"to":[-8.167,0,0],"ti":[-111.333,0,0]},{"i":{"x":0,"y":1},"o":{"x":0.167,"y":0},"t":141,"s":[251.75,276.75,0],"to":[111.333,0,0],"ti":[-119.5,0,0]},{"t":159,"s":[968.75,276.75,0]}],"ix":2},"a":{"a":0,"k":[125,125,0],"ix":1},"s":{"a":0,"k":[227,227,100],"ix":6}},"ao":0,"shapes":[{"ty":"gr","it":[{"ind":0,"ty":"sh","ix":1,"ks":{"a":0,"k":{"i":[[7.732,0],[0,0],[0,7.732],[0,0]],"o":[[0,0],[-7.732,0],[0,0],[0,7.732]],"v":[[89,7],[-89,7],[-103,-7],[103,-7]],"c":true},"ix":2},"nm":"Path 1","mn":"ADBE Vector Shape - Group","hd":false},{"ty":"fl","c":{"a":0,"k":[0.141000007181,0.086000001197,0.438999998803,1],"ix":4},"o":{"a":0,"k":100,"ix":5},"r":1,"bm":0,"nm":"Fill 1","mn":"ADBE Vector Graphic - Fill","hd":false},{"ty":"tr","p":{"a":0,"k":[125,196],"ix":2},"a":{"a":0,"k":[0,0],"ix":1},"s":{"a":0,"k":[100,100],"ix":3},"r":{"a":0,"k":0,"ix":6},"o":{"a":0,"k":100,"ix":7},"sk":{"a":0,"k":0,"ix":4},"sa":{"a":0,"k":0,"ix":5},"nm":"Transform"}],"nm":"Group 1","np":2,"cix":2,"bm":0,"ix":1,"mn":"ADBE Vector Group","hd":false}],"ip":0,"op":600,"st":0,"bm":0},{"ddd":0,"ind":6,"ty":4,"nm":"screen Outlines","sr":1,"ks":{"o":{"a":1,"k":[{"i":{"x":[0.833],"y":[0.833]},"o":{"x":[0.167],"y":[0.167]},"t":558,"s":[100]},{"t":593,"s":[0]}],"ix":11},"r":{"a":0,"k":0,"ix":10},"p":{"a":1,"k":[{"i":{"x":0.833,"y":0.833},"o":{"x":0.167,"y":0.167},"t":558,"s":[98.75,258.335,0],"to":[75.5,0,0],"ti":[-75.5,0,0]},{"t":593,"s":[551.75,258.335,0]}],"ix":2},"a":{"a":1,"k":[{"i":{"x":0.667,"y":1},"o":{"x":0.333,"y":0},"t":328,"s":[36.013,116.888,0],"to":[-22.5,0,0],"ti":[22.5,0,0]},{"t":363,"s":[-98.987,116.888,0]}],"ix":1},"s":{"a":1,"k":[{"i":{"x":[0,0.667,0.667],"y":[1,1,1]},"o":{"x":[0.333,0.333,0.333],"y":[0,0,0]},"t":46,"s":[0,227,100]},{"i":{"x":[0.833,0.833,0.833],"y":[1,1,1]},"o":{"x":[0.333,0.333,0.333],"y":[0,0,0]},"t":75,"s":[227,227,100]},{"i":{"x":[0.833,0.833,0.833],"y":[1,1,1]},"o":{"x":[0.167,0.167,0.167],"y":[0,0,0]},"t":177,"s":[227,227,100]},{"i":{"x":[0.685,0.685,0.685],"y":[1,1,1]},"o":{"x":[0.157,0.157,0.157],"y":[0,0,0]},"t":194,"s":[211,227,100]},{"i":{"x":[0.785,0.785,0.785],"y":[1,1,1]},"o":{"x":[0.432,0.432,0.432],"y":[0,0,0]},"t":324,"s":[211,227,100]},{"t":359,"s":[88,227,100]}],"ix":6}},"ao":0,"shapes":[{"ty":"gr","it":[{"ind":0,"ty":"sh","ix":1,"ks":{"a":0,"k":{"i":[[3.755,0],[0,0],[0,3.755],[0,0],[-3.276,0],[0,0],[0,-3.755],[0,0]],"o":[[0,0],[-3.756,0],[0,0],[0,-3.277],[0,0],[3.755,0],[0,0],[0,3.755]],"v":[[82.2,50.993],[-82.2,50.993],[-89,44.194],[-89,-45.059],[-83.067,-50.993],[82.2,-50.993],[89,-44.193],[89,44.194]],"c":true},"ix":2},"nm":"Path 1","mn":"ADBE Vector Shape - Group","hd":false},{"ty":"fl","c":{"a":0,"k":[1,1,1,1],"ix":4},"o":{"a":0,"k":100,"ix":5},"r":1,"bm":0,"nm":"Fill 1","mn":"ADBE Vector Graphic - Fill","hd":false},{"ty":"tr","p":{"a":0,"k":[125,116.007],"ix":2},"a":{"a":0,"k":[0,0],"ix":1},"s":{"a":0,"k":[100,100],"ix":3},"r":{"a":0,"k":0,"ix":6},"o":{"a":0,"k":100,"ix":7},"sk":{"a":0,"k":0,"ix":4},"sa":{"a":0,"k":0,"ix":5},"nm":"Transform"}],"nm":"Group 1","np":2,"cix":2,"bm":0,"ix":1,"mn":"ADBE Vector Group","hd":false}],"ip":0,"op":600,"st":0,"bm":0},{"ddd":0,"ind":7,"ty":4,"nm":"swicth Outlines","sr":1,"ks":{"o":{"a":1,"k":[{"i":{"x":[0.833],"y":[0.833]},"o":{"x":[0.167],"y":[0.167]},"t":558,"s":[100]},{"t":593,"s":[0]}],"ix":11},"r":{"a":0,"k":0,"ix":10},"p":{"a":1,"k":[{"i":{"x":0.232,"y":1},"o":{"x":0.333,"y":0},"t":147,"s":[300.75,393.655,0],"to":[0,-18.667,0],"ti":[0,21.333,0]},{"i":{"x":0.232,"y":1},"o":{"x":0.333,"y":0},"t":161,"s":[300.75,281.655,0],"to":[0,-21.333,0],"ti":[-31.833,3,0]},{"i":{"x":0.232,"y":1},"o":{"x":0.333,"y":0},"t":212,"s":[300.75,265.655,0],"to":[31.833,-3,0],"ti":[-31.833,0.333,0]},{"i":{"x":0.232,"y":0.232},"o":{"x":0.333,"y":0.333},"t":229,"s":[491.75,263.655,0],"to":[0,0,0],"ti":[0,0,0]},{"i":{"x":0.667,"y":1},"o":{"x":0.768,"y":0},"t":278,"s":[491.75,263.655,0],"to":[-31.833,0.333,0],"ti":[32.833,-14.333,0]},{"i":{"x":0.667,"y":1},"o":{"x":0.333,"y":0},"t":295,"s":[300.75,265.655,0],"to":[-32.833,14.333,0],"ti":[1,-20.667,0]},{"i":{"x":0.667,"y":1},"o":{"x":0.333,"y":0},"t":392,"s":[294.75,349.655,0],"to":[-1,20.667,0],"ti":[0,-6.667,0]},{"i":{"x":0.667,"y":0.667},"o":{"x":0.333,"y":0.333},"t":419,"s":[294.75,389.655,0],"to":[0,0,0],"ti":[0,0,0]},{"i":{"x":0.667,"y":1},"o":{"x":0.333,"y":0},"t":558,"s":[294.75,389.655,0],"to":[75.5,0,0],"ti":[-75.5,0,0]},{"t":593,"s":[747.75,389.655,0]}],"ix":2},"a":{"a":0,"k":[125,176.5,0],"ix":1},"s":{"a":1,"k":[{"i":{"x":[0,0,0.667],"y":[1,1,1]},"o":{"x":[0.333,0.333,0.333],"y":[0,0,0]},"t":75,"s":[0,0,100]},{"t":90,"s":[227,227,100]}],"ix":6}},"ao":0,"shapes":[{"ty":"gr","it":[{"ind":0,"ty":"sh","ix":1,"ks":{"a":0,"k":{"i":[[0,-2.485],[2.485,0],[0,2.485],[-2.485,0]],"o":[[0,2.485],[-2.485,0],[0,-2.485],[2.485,0]],"v":[[4.5,0],[0,4.5],[-4.5,0],[0,-4.5]],"c":true},"ix":2},"nm":"Path 1","mn":"ADBE Vector Shape - Group","hd":false},{"ty":"fl","c":{"a":0,"k":[1,1,1,1],"ix":4},"o":{"a":0,"k":100,"ix":5},"r":1,"bm":0,"nm":"Fill 1","mn":"ADBE Vector Graphic - Fill","hd":false},{"ty":"tr","p":{"a":0,"k":[125,176.5],"ix":2},"a":{"a":0,"k":[0,0],"ix":1},"s":{"a":0,"k":[100,100],"ix":3},"r":{"a":0,"k":0,"ix":6},"o":{"a":0,"k":100,"ix":7},"sk":{"a":0,"k":0,"ix":4},"sa":{"a":0,"k":0,"ix":5},"nm":"Transform"}],"nm":"Group 1","np":2,"cix":2,"bm":0,"ix":1,"mn":"ADBE Vector Group","hd":false}],"ip":0,"op":600,"st":0,"bm":0},{"ddd":0,"ind":8,"ty":4,"nm":"tab switch 2","sr":1,"ks":{"o":{"a":1,"k":[{"i":{"x":[0.833],"y":[0.833]},"o":{"x":[0.167],"y":[0.167]},"t":558,"s":[100]},{"t":593,"s":[0]}],"ix":11},"r":{"a":0,"k":0,"ix":10},"p":{"a":1,"k":[{"i":{"x":0,"y":1},"o":{"x":0.333,"y":0},"t":209,"s":[190,128.75,0],"to":[0,-0.333,0],"ti":[-12.333,0.833,0]},{"i":{"x":0,"y":1},"o":{"x":0.333,"y":0},"t":226,"s":[190,126.75,0],"to":[12.333,-0.833,0],"ti":[-12.333,0.5,0]},{"i":{"x":0,"y":0},"o":{"x":0.333,"y":0.333},"t":238,"s":[264,123.75,0],"to":[0,0,0],"ti":[0,0,0]},{"i":{"x":0.667,"y":1},"o":{"x":1,"y":0},"t":263,"s":[264,123.75,0],"to":[-12.333,0.5,0],"ti":[12.333,-0.833,0]},{"i":{"x":0.667,"y":1},"o":{"x":1,"y":0},"t":275,"s":[190,126.75,0],"to":[-12.333,0.833,0],"ti":[0,-0.333,0]},{"i":{"x":0.667,"y":0.667},"o":{"x":0.333,"y":0.333},"t":292,"s":[190,128.75,0],"to":[0,0,0],"ti":[0,0,0]},{"i":{"x":0.667,"y":1},"o":{"x":0.333,"y":0},"t":558,"s":[190,128.75,0],"to":[75.5,0,0],"ti":[-75.5,0,0]},{"t":593,"s":[643,128.75,0]}],"ix":2},"a":{"a":0,"k":[125,59.802,0],"ix":1},"s":{"a":0,"k":[20,13,100],"ix":6}},"ao":0,"shapes":[{"ty":"gr","it":[{"ind":0,"ty":"sh","ix":1,"ks":{"a":0,"k":{"i":[[4.261,0],[0,0],[0,4.261],[0,0],[-3.719,0],[0,0],[0,-4.261],[0,0]],"o":[[0,0],[-4.262,0],[0,0],[0,-3.718],[0,0],[4.261,0],[0,0],[0,4.261]],"v":[[85.784,62.5],[-85.784,62.5],[-93.5,54.784],[-93.5,-55.767],[-86.767,-62.5],[85.784,-62.5],[93.5,-54.784],[93.5,54.784]],"c":true},"ix":2},"nm":"Path 1","mn":"ADBE Vector Shape - Group","hd":false},{"ty":"fl","c":{"a":0,"k":[0.435000011968,0.301999978458,1,1],"ix":4},"o":{"a":0,"k":100,"ix":5},"r":1,"bm":0,"nm":"Fill 1","mn":"ADBE Vector Graphic - Fill","hd":false},{"ty":"tr","p":{"a":0,"k":[125,122.5],"ix":2},"a":{"a":0,"k":[0,0],"ix":1},"s":{"a":0,"k":[100,100],"ix":3},"r":{"a":0,"k":0,"ix":6},"o":{"a":0,"k":100,"ix":7},"sk":{"a":0,"k":0,"ix":4},"sa":{"a":0,"k":0,"ix":5},"nm":"Transform"}],"nm":"Group 1","np":2,"cix":2,"bm":0,"ix":1,"mn":"ADBE Vector Group","hd":false}],"ip":208,"op":300,"st":-3,"bm":0},{"ddd":0,"ind":9,"ty":4,"nm":"tab switch","sr":1,"ks":{"o":{"a":1,"k":[{"i":{"x":[0.833],"y":[0.833]},"o":{"x":[0.167],"y":[0.167]},"t":558,"s":[100]},{"t":593,"s":[0]}],"ix":11},"r":{"a":0,"k":0,"ix":10},"p":{"a":1,"k":[{"i":{"x":0,"y":1},"o":{"x":0.333,"y":0},"t":209,"s":[190,128.75,0],"to":[0,-0.833,0],"ti":[0,0.833,0]},{"i":{"x":0,"y":0},"o":{"x":0.333,"y":0.333},"t":226,"s":[190,123.75,0],"to":[0,0,0],"ti":[0,0,0]},{"i":{"x":0.667,"y":1},"o":{"x":1,"y":0},"t":263,"s":[190,123.75,0],"to":[0,0.833,0],"ti":[0,-0.833,0]},{"i":{"x":0.667,"y":0.667},"o":{"x":0.333,"y":0.333},"t":280,"s":[190,128.75,0],"to":[0,0,0],"ti":[0,0,0]},{"i":{"x":0.667,"y":1},"o":{"x":0.333,"y":0},"t":558,"s":[190,128.75,0],"to":[75.5,0,0],"ti":[-75.5,0,0]},{"t":593,"s":[643,128.75,0]}],"ix":2},"a":{"a":0,"k":[125,59.802,0],"ix":1},"s":{"a":0,"k":[45,25,100],"ix":6}},"ao":0,"shapes":[{"ty":"gr","it":[{"ind":0,"ty":"sh","ix":1,"ks":{"a":0,"k":{"i":[[4.261,0],[0,0],[0,4.261],[0,0],[-3.719,0],[0,0],[0,-4.261],[0,0]],"o":[[0,0],[-4.262,0],[0,0],[0,-3.718],[0,0],[4.261,0],[0,0],[0,4.261]],"v":[[85.784,62.5],[-85.784,62.5],[-93.5,54.784],[-93.5,-55.767],[-86.767,-62.5],[85.784,-62.5],[93.5,-54.784],[93.5,54.784]],"c":true},"ix":2},"nm":"Path 1","mn":"ADBE Vector Shape - Group","hd":false},{"ty":"fl","c":{"a":0,"k":[0.435000011968,0.301999978458,1,1],"ix":4},"o":{"a":0,"k":100,"ix":5},"r":1,"bm":0,"nm":"Fill 1","mn":"ADBE Vector Graphic - Fill","hd":false},{"ty":"tr","p":{"a":0,"k":[125,122.5],"ix":2},"a":{"a":0,"k":[0,0],"ix":1},"s":{"a":0,"k":[100,100],"ix":3},"r":{"a":0,"k":0,"ix":6},"o":{"a":0,"k":100,"ix":7},"sk":{"a":0,"k":0,"ix":4},"sa":{"a":0,"k":0,"ix":5},"nm":"Transform"}],"nm":"Group 1","np":2,"cix":2,"bm":0,"ix":1,"mn":"ADBE Vector Group","hd":false}],"ip":208,"op":300,"st":-3,"bm":0},{"ddd":0,"ind":10,"ty":4,"nm":"mobile_switch 2","sr":1,"ks":{"o":{"a":1,"k":[{"i":{"x":[0.833],"y":[0.833]},"o":{"x":[0.167],"y":[0.167]},"t":558,"s":[100]},{"t":593,"s":[0]}],"ix":11},"r":{"a":0,"k":0,"ix":10},"p":{"a":1,"k":[{"i":{"x":0,"y":1},"o":{"x":0.333,"y":0},"t":419,"s":[374.75,157.75,0],"to":[0.5,0,0],"ti":[-0.5,-12,0]},{"i":{"x":0,"y":1},"o":{"x":0.333,"y":0},"t":445,"s":[377.75,157.75,0],"to":[0.5,12,0],"ti":[0,-12,0]},{"i":{"x":0,"y":0},"o":{"x":0.333,"y":0.333},"t":473,"s":[377.75,229.75,0],"to":[0,0,0],"ti":[0,0,0]},{"i":{"x":0,"y":1},"o":{"x":0.333,"y":0},"t":558,"s":[377.75,229.75,0],"to":[75.5,0,0],"ti":[-75.5,0,0]},{"t":593,"s":[830.75,229.75,0]}],"ix":2},"a":{"a":0,"k":[131,59.802,0],"ix":1},"s":{"a":1,"k":[{"i":{"x":[0,0.667,0.667],"y":[1,1,1]},"o":{"x":[0.333,0.333,0.333],"y":[0,0,0]},"t":419,"s":[8,47,100]},{"t":445,"s":[8,21,100]}],"ix":6}},"ao":0,"shapes":[{"ty":"gr","it":[{"ind":0,"ty":"sh","ix":1,"ks":{"a":0,"k":{"i":[[4.261,0],[0,0],[0,4.261],[0,0],[-3.719,0],[0,0],[0,-4.261],[0,0]],"o":[[0,0],[-4.262,0],[0,0],[0,-3.718],[0,0],[4.261,0],[0,0],[0,4.261]],"v":[[85.784,62.5],[-85.784,62.5],[-93.5,54.784],[-93.5,-55.767],[-86.767,-62.5],[85.784,-62.5],[93.5,-54.784],[93.5,54.784]],"c":true},"ix":2},"nm":"Path 1","mn":"ADBE Vector Shape - Group","hd":false},{"ty":"fl","c":{"a":0,"k":[0.435000011968,0.301999978458,1,1],"ix":4},"o":{"a":0,"k":100,"ix":5},"r":1,"bm":0,"nm":"Fill 1","mn":"ADBE Vector Graphic - Fill","hd":false},{"ty":"tr","p":{"a":0,"k":[125,122.5],"ix":2},"a":{"a":0,"k":[0,0],"ix":1},"s":{"a":0,"k":[100,100],"ix":3},"r":{"a":0,"k":0,"ix":6},"o":{"a":0,"k":100,"ix":7},"sk":{"a":0,"k":0,"ix":4},"sa":{"a":0,"k":0,"ix":5},"nm":"Transform"}],"nm":"Group 1","np":2,"cix":2,"bm":0,"ix":1,"mn":"ADBE Vector Group","hd":false}],"ip":415,"op":626,"st":0,"bm":0},{"ddd":0,"ind":11,"ty":4,"nm":"mobile_switch","sr":1,"ks":{"o":{"a":1,"k":[{"i":{"x":[0.833],"y":[0.833]},"o":{"x":[0.167],"y":[0.167]},"t":558,"s":[100]},{"t":593,"s":[0]}],"ix":11},"r":{"a":0,"k":0,"ix":10},"p":{"a":1,"k":[{"i":{"x":0,"y":1},"o":{"x":0.333,"y":0},"t":419,"s":[374.75,157.75,0],"to":[0.5,0,0],"ti":[-0.5,0,0]},{"i":{"x":0,"y":0},"o":{"x":0.333,"y":0.333},"t":445,"s":[377.75,157.75,0],"to":[0,0,0],"ti":[0,0,0]},{"i":{"x":0,"y":1},"o":{"x":0.333,"y":0},"t":558,"s":[377.75,157.75,0],"to":[75.5,0,0],"ti":[-75.5,0,0]},{"t":593,"s":[830.75,157.75,0]}],"ix":2},"a":{"a":0,"k":[131,59.802,0],"ix":1},"s":{"a":1,"k":[{"i":{"x":[0,0.667,0.667],"y":[1,1,1]},"o":{"x":[0.333,0.333,0.333],"y":[0,0,0]},"t":419,"s":[8,47,100]},{"t":445,"s":[8,47,100]}],"ix":6}},"ao":0,"shapes":[{"ty":"gr","it":[{"ind":0,"ty":"sh","ix":1,"ks":{"a":0,"k":{"i":[[4.261,0],[0,0],[0,4.261],[0,0],[-3.719,0],[0,0],[0,-4.261],[0,0]],"o":[[0,0],[-4.262,0],[0,0],[0,-3.718],[0,0],[4.261,0],[0,0],[0,4.261]],"v":[[85.784,62.5],[-85.784,62.5],[-93.5,54.784],[-93.5,-55.767],[-86.767,-62.5],[85.784,-62.5],[93.5,-54.784],[93.5,54.784]],"c":true},"ix":2},"nm":"Path 1","mn":"ADBE Vector Shape - Group","hd":false},{"ty":"fl","c":{"a":0,"k":[0.435000011968,0.301999978458,1,1],"ix":4},"o":{"a":0,"k":100,"ix":5},"r":1,"bm":0,"nm":"Fill 1","mn":"ADBE Vector Graphic - Fill","hd":false},{"ty":"tr","p":{"a":0,"k":[125,122.5],"ix":2},"a":{"a":0,"k":[0,0],"ix":1},"s":{"a":0,"k":[100,100],"ix":3},"r":{"a":0,"k":0,"ix":6},"o":{"a":0,"k":100,"ix":7},"sk":{"a":0,"k":0,"ix":4},"sa":{"a":0,"k":0,"ix":5},"nm":"Transform"}],"nm":"Group 1","np":2,"cix":2,"bm":0,"ix":1,"mn":"ADBE Vector Group","hd":false}],"ip":415,"op":626,"st":0,"bm":0},{"ddd":0,"ind":12,"ty":4,"nm":"body Outlines","sr":1,"ks":{"o":{"a":1,"k":[{"i":{"x":[0.833],"y":[0.833]},"o":{"x":[0.167],"y":[0.167]},"t":558,"s":[100]},{"t":593,"s":[0]}],"ix":11},"r":{"a":0,"k":0,"ix":10},"p":{"a":1,"k":[{"i":{"x":0.833,"y":0.833},"o":{"x":0.167,"y":0.167},"t":558,"s":[300.75,128.75,0],"to":[75.5,0,0],"ti":[-75.5,0,0]},{"t":593,"s":[753.75,128.75,0]}],"ix":2},"a":{"a":1,"k":[{"i":{"x":0.833,"y":0.833},"o":{"x":0.167,"y":0.167},"t":347,"s":[125,59.802,0],"to":[1,0,0],"ti":[-1,0,0]},{"t":367,"s":[131,59.802,0]}],"ix":1},"s":{"a":1,"k":[{"i":{"x":[0,0.667,0.667],"y":[1,1,1]},"o":{"x":[0.333,0.333,0.333],"y":[0,0,0]},"t":33,"s":[0,227,100]},{"i":{"x":[0.391,0.176,0.833],"y":[1,1,1]},"o":{"x":[0.167,0.167,0.167],"y":[0,0,0]},"t":63,"s":[227,227,100]},{"i":{"x":[0,0,0.833],"y":[1,1,1]},"o":{"x":[0.167,0.167,0.167],"y":[0,0,0]},"t":153,"s":[227,227,100]},{"i":{"x":[0.833,0.833,0.833],"y":[1,1,1]},"o":{"x":[0.167,0.167,0.167],"y":[0,0,0]},"t":177,"s":[227,205,100]},{"i":{"x":[0.833,0.833,0.833],"y":[1,1,1]},"o":{"x":[0.167,0.167,0.167],"y":[0,0,0]},"t":347,"s":[227,205,100]},{"i":{"x":[0.833,0.833,0.833],"y":[1,1,1]},"o":{"x":[0.167,0.167,0.167],"y":[0,0,0]},"t":367,"s":[93,205,100]},{"t":394,"s":[93,226,100]}],"ix":6}},"ao":0,"shapes":[{"ty":"gr","it":[{"ind":0,"ty":"sh","ix":1,"ks":{"a":0,"k":{"i":[[4.261,0],[0,0],[0,4.261],[0,0],[-3.719,0],[0,0],[0,-4.261],[0,0]],"o":[[0,0],[-4.262,0],[0,0],[0,-3.718],[0,0],[4.261,0],[0,0],[0,4.261]],"v":[[85.784,62.5],[-85.784,62.5],[-93.5,54.784],[-93.5,-55.767],[-86.767,-62.5],[85.784,-62.5],[93.5,-54.784],[93.5,54.784]],"c":true},"ix":2},"nm":"Path 1","mn":"ADBE Vector Shape - Group","hd":false},{"ty":"fl","c":{"a":0,"k":[0.435000011968,0.301999978458,1,1],"ix":4},"o":{"a":0,"k":100,"ix":5},"r":1,"bm":0,"nm":"Fill 1","mn":"ADBE Vector Graphic - Fill","hd":false},{"ty":"tr","p":{"a":0,"k":[125,122.5],"ix":2},"a":{"a":0,"k":[0,0],"ix":1},"s":{"a":0,"k":[100,100],"ix":3},"r":{"a":0,"k":0,"ix":6},"o":{"a":0,"k":100,"ix":7},"sk":{"a":0,"k":0,"ix":4},"sa":{"a":0,"k":0,"ix":5},"nm":"Transform"}],"nm":"Group 1","np":2,"cix":2,"bm":0,"ix":1,"mn":"ADBE Vector Group","hd":false}],"ip":0,"op":600,"st":0,"bm":0}],"markers":[]}